dbjson/__init__.py
dbjson/cli.py
dbjson/dbjson.py
dbjson/utils.py
dbjsonpy-1.0.7.dist-info/LICENSE
dbjsonpy-1.0.7.dist-info/METADATA
dbjsonpy-1.0.7.dist-info/WHEEL
dbjsonpy-1.0.7.dist-info/top_level.txt
dbjsonpy-1.0.7.dist-info/RECORD
