Metadata-Version: 2.1
Name: dbjsonpy
Version: 1.0.7
Summary: crud operation with database using json.
Home-page: https://github.com/jakbin/dbjson
Author: Jak Bin
Author-email: jakbin4747@gmail.com
License: MIT License
Keywords: dbjson,database,json
Classifier: Programming Language :: Python :: 3.6
Classifier: Natural Language :: English
Classifier: Operating System :: OS Independent
Requires-Python: >=3
License-File: LICENSE
Requires-Dist: sqlalchemy
